[
  {
    "file": "https://yourcdn.com/audio/forest.mp3",
    "title": "森林雨聲",
    "tag": ["森林","雨聲"],
    "desc": "森林中的細雨聲，帶來寧靜與療癒。",
    "embedding": [0.001, -0.003, 0.014]
  },
  {
    "file": "https://yourcdn.com/audio/ocean.mp3",
    "title": "Ocean Waves",
    "tag": ["ocean", "waves", "calm", "beach"],
    "desc": "Soothing ocean waves for deep sleep or relaxation.",
    "embedding": [0.001, -0.003, 0.014]
  },
  {
    "file": "https://yourcdn.com/audio/whitenoise.mp3",
    "title": "White Noise",
    "tag": ["white noise", "focus", "work", "sleep"],
    "desc": "Classic white noise for masking distractions.",
    "embedding": [0.001, -0.003, 0.014]
  }
]